mtls/__init__.py
mtls/__main__.py
mtls/__version__.py
mtls/cli.py
mtls/mtls.py
mtls-0.17.0.dist-info/LICENSE
mtls-0.17.0.dist-info/METADATA
mtls-0.17.0.dist-info/WHEEL
mtls-0.17.0.dist-info/entry_points.txt
mtls-0.17.0.dist-info/top_level.txt
mtls-0.17.0.dist-info/zip-safe
mtls-0.17.0.dist-info/RECORD
