Metadata-Version: 2.1
Name: mtls
Version: 0.17.0
Summary: A short-lived certificate tool based on the Zero Trust network mode
Home-page: https://github.com/drGrove/mtls-cli
Author-email: Danny Grove <danny@drgrovellc.com>
License: Copyright 2018-2022 Danny Grove        
Project-URL: Homepage, https://github.com/drGrove/mtls-cli
Project-URL: Source, https://github.com/drGrove/mtls-cli
Project-URL: Tracker, https://github.com/drGrove/mtls-cli/issues
Platform: UNKNOWN
Classifier: Development Status :: 4 - Beta
Classifier: Intended Audience :: Developers
Classifier: Intended Audience :: End Users/Desktop
Classifier: Intended Audience :: System Administrators
Classifier: License :: OSI Approved :: Apache Software License
Classifier: Operating System :: OS Independent
Classifier: Topic :: Internet
Classifier: Topic :: Security :: Cryptography
Classifier: Topic :: Security
Classifier: Topic :: Software Development :: Libraries :: Python Modules
Classifier: Programming Language :: Python :: 3
Classifier: Programming Language :: Python :: 3.8
Classifier: Programming Language :: Python :: 3.9
Classifier: Programming Language :: Python :: 3.10
Classifier: Programming Language :: Python :: 3 :: Only
Requires-Python: >=3.8
License-File: LICENSE
Requires-Dist: cryptography
Requires-Dist: python-gnupg
Requires-Dist: urllib3
Requires-Dist: requests
Requires-Dist: click
Requires-Dist: pyOpenSSL
